__init__.py
pipeline.py
autoincorrect-0.0.2.dist-info/licenses/LICENSE
autoincorrect-0.0.2.dist-info/METADATA
autoincorrect-0.0.2.dist-info/WHEEL
autoincorrect-0.0.2.dist-info/top_level.txt
autoincorrect-0.0.2.dist-info/RECORD
