Metadata-Version: 2.4
Name: autoINcorrect
Version: 0.0.2
Summary: A package to intentionally introduce human-like errors into text.
Author-email: Ronak Daniel <danielronak8105@email.com>
License: MIT
Classifier: Programming Language :: Python :: 3
Classifier: License :: OSI Approved :: MIT License
Classifier: Operating System :: OS Independent
Classifier: Topic :: Scientific/Engineering :: Artificial Intelligence
Classifier: Topic :: Software Development :: Libraries :: Python Modules
Classifier: Topic :: Text Processing
Requires-Python: >=3.8
License-File: LICENSE
Requires-Dist: nltk
Requires-Dist: gensim
Dynamic: license-file
